[
  {
    "name": "John",
    "surname": "Doe",
    "email": "johndoe@example.com"
  },
  {
    "name": "Jane",
    "surname": "MeDoe",
    "email": "janemedoe@example.com"
  },
  {
    "name": "David",
    "surname": "Smith",
    "email": "davidsmith@example.com"
  },
  {
    "name": "Emily",
    "surname": "Jones",
    "email": "emilyjones@example.com"
  },
  {
    "name": "Michael",
    "surname": "Brown",
    "email": "michaelbrown@example.com"
  },
  {
    "name": "Sarah",
    "surname": "Johnson",
    "email": "sarahjohnson@example.com"
  },
  {
    "name": "Steven",
    "surname": "Wilson",
    "email": "stevenwilson@example.com"
  },
  {
    "name": "Rachel",
    "surname": "Davis",
    "email": "racheldavis@example.com"
  },
  {
    "name": "Christopher",
    "surname": "Taylor",
    "email": "christophertaylor@example.com"
  },
  {
    "name": "Melissa",
    "surname": "Anderson",
    "email": "melissaanderson@example.com"
  },
  {
    "name": "Robert",
    "surname": "Miller",
    "email": "robertmiller@example.com"
  },
  {
    "name": "Megan",
    "surname": "Wilson",
    "email": "meganwilson@example.com"
  },
  {
    "name": "Brandon",
    "surname": "Thompson",
    "email": "brandonthompson@example.com"
  },
  {
    "name": "Ashley",
    "surname": "Johnson",
    "email": "ashleyjohnson@example.com"
  },
  {
    "name": "Matthew",
    "surname": "Garcia",
    "email": "matthewgarcia@example.com"
  },
  {
    "name": "Lauren",
    "surname": "Lee",
    "email": "laurenlee@example.com"
  },
  {
    "name": "Daniel",
    "surname": "Hall",
    "email": "danielhall@example.com"
  },
  {
    "name": "Hannah",
    "surname": "Gonzalez",
    "email": "hannahgonzalez@example.com"
  },
  {
    "name": "Joshua",
    "surname": "Harris",
    "email": "joshuaharris@example.com"
  },
  {
    "name": "Stephanie",
    "surname": "Clark",
    "email": "stephanieclark@example.com"
  },
  {
    "name": "Kevin",
    "surname": "Jackson",
    "email": "kevinjackson@example.com"
  },
  {
    "name": "Amanda",
    "surname": "Wright",
    "email": "amandawright@example.com"
  },
  {
    "name": "Justin",
    "surname": "Lewis",
    "email": "justinlewis@example.com"
  },
  {
    "name": "Kaitlyn",
    "surname": "Green",
    "email": "kaitlyngreen@example.com"
  }
]